<annotation>
	<folder>images</folder>
	<filename>hyperbola56.jpg</filename>
	<path>/home/irerenu/Documents/projects/gpr-data-classifier/hyperbola-classifier/images/hyperbola56.jpg</path>
	<source>
		<database>Unknown</database>
	</source>
	<size>
		<width>459</width>
		<height>415</height>
		<depth>3</depth>
	</size>
	<segmented>0</segmented>
	<object>
		<name>hyperbola</name>
		<pose>Unspecified</pose>
		<truncated>0</truncated>
		<difficult>0</difficult>
		<bndbox>
			<xmin>289</xmin>
			<ymin>233</ymin>
			<xmax>317</xmax>
			<ymax>274</ymax>
		</bndbox>
	</object>
	<object>
		<name>hyperbola</name>
		<pose>Unspecified</pose>
		<truncated>0</truncated>
		<difficult>0</difficult>
		<bndbox>
			<xmin>391</xmin>
			<ymin>231</ymin>
			<xmax>412</xmax>
			<ymax>267</ymax>
		</bndbox>
	</object>
</annotation>
